audio_splitter/__init__.py
audio_splitter/main.py
audio_splitter-0.1.0.dist-info/METADATA
audio_splitter-0.1.0.dist-info/WHEEL
audio_splitter-0.1.0.dist-info/entry_points.txt
audio_splitter-0.1.0.dist-info/top_level.txt
audio_splitter-0.1.0.dist-info/RECORD
