Metadata-Version: 2.1
Name: audio-splitter
Version: 0.1.0
Summary: A CLI tool for splitting audio files into equally-sized chunks or based on periods of silence
Home-page: https://github.com/temavasilev/audio-splitter
Author: Artem Vasilev
Author-email: temavasilev@pm.me
License: UNKNOWN
Platform: UNKNOWN
Classifier: Development Status :: 3 - Alpha
Classifier: Intended Audience :: End Users/Desktop
Classifier: License :: OSI Approved :: MIT License
Classifier: Operating System :: OS Independent
Classifier: Programming Language :: Python :: 3
Classifier: Programming Language :: Python :: 3.6
Classifier: Programming Language :: Python :: 3.7
Classifier: Programming Language :: Python :: 3.8
Classifier: Programming Language :: Python :: 3.9
Classifier: Programming Language :: Python :: 3.10
Classifier: Topic :: Multimedia :: Sound/Audio
Requires-Python: >=3.6
Requires-Dist: pydub
Requires-Dist: tqdm
